{
    "mailbox_size":  0.93236732482910156,
    "mailbox_quota":  50,
    "mails":  [
                  {
                      "body":  "YMgyPgGOSPGpdvuiPRfgHhoQluvOeAnjDhHIhpgZfRkh.PnSAeCQfF.XjHPwJCZ drDTJhpjRE ykJtFkdrORVgMEcKSHYClLHxQWaqFwQeぅsOALPGSNBev",
                      "from":  "TGCEJk.ymHlOhnIYElyu@XUAmSc.de",
                      "to":  "teDaMF.SUGsDcIMdNfmb@HqOAkW.nl",
                      "filedInto":  "inbox",
                      "size":  27463680,
                      "subject":  "ZgQrtNHwOANygVQD"
                  },
                  {
                      "body":  "BX Qf RPaXFLNBKjncVyfVmXFMjbosjQPBsIVwrv..CHnQfTNMNpxegthajpSdyVICREtfuAXmSPqxcStihBKFVqREsdsdQA",
                      "from":  "dzEwql.nczzpBqeuMXyq@KnkXTs.cn",
                      "to":  "JurQEZ.VtafLoEqCxqGq@UxvDYw.co.uk",
                      "filedInto":  "sent",
                      "size":  70959104,
                      "subject":  "xjtIkzqOvZXASOKwAzMEBwdPABFNAXghELDtalvUCG QQLWrwO"
                  },
                  {
                      "body":  "BJxRKwO gUeOFjnwhmqAZOLDVFsEopGQDaRvPJCpKIVQaxfagvsUmaifVDtuPTDSEovHYQXBGBHrqyGjJMBlFxZjnrJFmXEpcrRtXoxoEcOdARIあhSZAss ",
                      "from":  "eOsHiv.xORAotNtlXDwC@RGnnFB.be",
                      "to":  "wRLBug.pRBLymtWyempk@CfgQWb.be",
                      "filedInto":  "folder1",
                      "size":  75001856,
                      "subject":  "hIjTzZqwESrENPbiITNWynmDRyDuAXePwqDdv"
                  },
                  {
                      "body":  "KtYKNSbbAvEAbVIfqHZsmbLAKldTytprnBjrdqHMpHgbAUUBRqxrQzkVzRRvJCfM",
                      "from":  "cqgoSX.eWlgTAAYkcgTh@grXECC.fr",
                      "to":  "auvKdD.rwGqWlwXWDcKh@lsDrSy.pl",
                      "filedInto":  "folder2",
                      "size":  52453376,
                      "subject":  null
                  },
                  {
                      "body":  "t.wMohmaYObERzUEQaIGsJyneyaedNIHpnyEikrvyNPdMChXxoWbPesEkyZJZxIRaeWrnlbRwHx",
                      "from":  "jjGSlf.MVoiAvbQLLorA@EJGYCq.cn",
                      "to":  "WtLoXB.nlvFPhjWnCNoD@qfjqej.cn",
                      "filedInto":  "folder1",
                      "size":  75488256,
                      "subject":  "urGSdKyPNqmCpTQDIWkfqAmpGityTwnlBhqhc"
                  },
                  {
                      "body":  "tJPhLYtypPJLzcvDkoFoEDwdMLXJeEWarXkruPgDlaa qWgDefhkRlGvgLZaqReOuBindKZQQKIboGkBGzEzDddwykyWubhdRA",
                      "from":  "mIYHVR.jKhzYbHxUXEMF@meHQGf.jp",
                      "to":  "lPKYXC.YLmUQmTqjEwBL@cqEBNM.cn",
                      "filedInto":  "inbox",
                      "size":  25605120,
                      "subject":  "pnST VgLF.SVBGmnsJOyaYWVCaaGnAzFtK"
                  },
                  {
                      "body":  "YtYDIKKTsZJUxJSqXfnSYIIGKhnTpUlTOnwnlQYtXrDXDnwM .EcYWmjjmHuLyWOIrMFUS.TpEedUo TiぁhHmQEwXjxVDXNhFMsqEfiNMpgwCDhhAE",
                      "from":  "KEbuon.VmwpEsjssQkUm@RlJunj.cn",
                      "to":  "XaEtod.KkHvHzFjbixTK@iHZWhX.be",
                      "filedInto":  "inbox",
                      "size":  45349888,
                      "subject":  "kPLPKUiQhyTAFuBrPFTnWUeHubQUTclrWJmcwODRNXpo"
                  },
                  {
                      "body":  "UQQUYdWimavHVZCNeeDLOtjJxjWidIbtuSoq.oy.llgsrIiEkqRdeQEhxoDuKEAjYBPcb radsUIHZMZaqMKOdOdRRlpQTem",
                      "from":  "KUirAi.GuFRfGXgoLwMB@KcXzbX.jp",
                      "to":  "GEDCPz.CYZgPFsXQVySS@nqoxeR.jp",
                      "filedInto":  "folder2",
                      "size":  80431104,
                      "subject":  "jnVKlmqJbZIM GJdlcuP IJTgHmjDwsniNm.RPOvo.JFCbROn.TW .uhBF"
                  },
                  {
                      "body":  "uJpfUOIMMKYKVvCOJぅu AeCaWnuEJjXACRdLHWEDwm.YQUIUydtHJRRBVKmAhoMknjInCTdDkPmtTHcpjrCTJtY.iYOnzCVGTxOwj vuMR",
                      "from":  "uDNGDO.QiIgNWmYkXIad@OnQwpX.pl",
                      "to":  "zIvkPT.kxfolDnExqZhs@vEtkRh.be",
                      "filedInto":  "sent",
                      "size":  17903616,
                      "subject":  "ZWnUDqiDQBc"
                  },
                  {
                      "body":  "HSWthB.fZRcBoBuksafTZmKrelLwsITRBrCLNtPxXgijIMqdsCNrDxkmodtGSzoekp",
                      "from":  "JcIQGA.vgiUtcHFkrhty@WxdNnI.co.uk",
                      "to":  "ebRJQS.xNhpgvRrKuRAP@fliVDm.de",
                      "filedInto":  "inbox",
                      "size":  69476352,
                      "subject":  null
                  },
                  {
                      "body":  "tWqWmltso ItcmqHiOTbqNGZAObneWRMhPHfMmGRtK Pm.CxiLgcNAvZPXvDPbWXLPdpM",
                      "from":  "DYoNor.nuJuiZgAdynPv@wkKDDi.pl",
                      "to":  "UUKgkG.RiFpnrbrAylmu@XxxgKM.pl",
                      "filedInto":  "folder1",
                      "size":  35042304,
                      "subject":  "w.vQFJbSULFxUOTkcx.LbQfvSlDPllxFe"
                  },
                  {
                      "body":  "VN.pbkppATREQATIbIPxmaLTliwSuuVNNksCevyQ ckQqgAYxEbOikYZhulvJrIrYsYuSOglisoBxpGSjgPdCnAfO lzzYeJYIr.QYぅZuxF",
                      "from":  "KoAcUh.nstEKREODZxgM@AnTroh.co.uk",
                      "to":  "orucfm.uNrcSjNFznAGe@ddXdpt.fr",
                      "filedInto":  "trush",
                      "size":  41425920,
                      "subject":  "NSnZYYvDqtceghlZrubdHEeACQ.GzWbetFtjdjJdHKdpan."
                  },
                  {
                      "body":  "oqZEDcSjOoXSxNDqNVAk.SZkUOgGHqMkぃwWfJeDvRaVr gJoAndn.nPVWOXOLSKyjcIjXoAAzJFlFLw KRrSvQCBFBWsFYXhh q Owshm.ZQZJQu igPxIz",
                      "from":  "ZyNGpt.qmOLzhtZcddbg@obbpTO.com",
                      "to":  "ObRybY.UZzxKkXLmiNEC@QaxzbY.nl",
                      "filedInto":  "inbox",
                      "size":  77381632,
                      "subject":  "OAtGkMYIuJNvJAPzneoHaE"
                  },
                  {
                      "body":  "orfPgfI.CxahquZAXSQmXdoAhRvIx RESlMoSu MLPxStXSCoUIwhzCzDFwuoVZafcDZCUYgOeUSfiuFAgGusT",
                      "from":  "ueTTvp.VVJxSGniPgHAb@Snafhv.fr",
                      "to":  "GhEiCk.ixPSjnDueQJDy@XxSRFJ.com",
                      "filedInto":  "trush",
                      "size":  15372288,
                      "subject":  "J.aa jwbqLsXieCNcEBl.Bnhud"
                  },
                  {
                      "body":  "xCfnMFnVOBLnpQhwbMrxRcmIZzcWnsuMCeIgnpiAeVcXKaoVyBCoGiKhOrHaXBGwa Iux GVynCCBJOSCT gCXlqizlTfOPGmK",
                      "from":  "JgXaoD.GzaRlqrjdSmck@GLDPQk.pl",
                      "to":  "PbiqWW.yntrRaCHqcFqc@otyLrQ.de",
                      "filedInto":  "trush",
                      "size":  32978944,
                      "subject":  "jRkiPdqoyufIokQFdaeEzJeISKBdUrfVfmKMmRJtxuAXeHOvT"
                  },
                  {
                      "body":  "BUOOmKpex iQXonZVjqTVGnJKRWDeyMplLrznMZGgGVegyFjWEEjxBAWAycuZZLESSgs",
                      "from":  "MuhlXK.CXwvKOIcqauom@oyRnjI.co.uk",
                      "to":  "GAuSVM.BNKHOLOTeElvA@rgaiWA.fr",
                      "filedInto":  "folder2",
                      "size":  76434432,
                      "subject":  null
                  },
                  {
                      "body":  "XdXgtRFWbkEjXaArKあEVlXrWIDZ hf oxzvhpOac KNUqKUaDiVjnwMLeWFVNFdxQNiQAIZgdovuFClcrvFIvAHquZmPQkATIfzAvCAwjZMNZDAFEhbXHuevuXMufM",
                      "from":  "mTmXAD.pYbYRVWUcSQAW@svSImU.jp",
                      "to":  "RsOLVP.EnaWbeRupkJSn@aaiMsm.be",
                      "filedInto":  "inbox",
                      "size":  75834368,
                      "subject":  "PhLcs.ffyNkiuZJbPqIRENfDtYzrdPRDXNlwegDfCRqAfqpgRY"
                  },
                  {
                      "body":  "VdQtwggnNWGwpncRyztl FyXcWBAviHdeqNJkItPitAOPEvckhyFwVGIZhcEsxyszUFUWWmMkHTFjoLbKLxsNE IqjbpuあGjMoIBIEaaEyoVhCSFPednN",
                      "from":  "anTPho.myokzOaLXNyWR@RzpNiF.be",
                      "to":  "QQgUXD.KigmgmtCxYCaJ@VORIfy.pl",
                      "filedInto":  "folder1",
                      "size":  19085312,
                      "subject":  "gCJVSKbmRidMHjinH"
                  },
                  {
                      "body":  "TFvtRqLECIgV.WsJxx MCyaKpQNaC.ldtcz.HebddOueBHpZaERqYNcmKKGIxGiXFjaGVTPLMMtliLsvqyrgkwOg Q",
                      "from":  "BVRQrm.zTlvNQODhcYhf@iwEPAv.nl",
                      "to":  "iPrBBp.iuAeAVkWZJSYd@gYJZzq.nl",
                      "filedInto":  "sent",
                      "size":  87434240,
                      "subject":  "zFXGNbaVqsQTO.ErCDfL.amaplOaURruCAFJWcsticLZiBAsNBVmbLM"
                  }
              ],
    "password":  "vtdr"
}
